ExchangeRateApi/ExchangeRateApi.py
ExchangeRateApi/__init__.py
ExchangeRateApi/exceptions.py
ExchangeRateApi/utils.py
ExchangeRateApi-0.1.0.dist-info/LICENSE
ExchangeRateApi-0.1.0.dist-info/METADATA
ExchangeRateApi-0.1.0.dist-info/WHEEL
ExchangeRateApi-0.1.0.dist-info/entry_points.txt
ExchangeRateApi-0.1.0.dist-info/top_level.txt
ExchangeRateApi-0.1.0.dist-info/RECORD
