Metadata-Version: 2.1
Name: ExchangeRateApi
Version: 0.1.0
Summary: This library uses the api functionality of ExchangeRateApi, it will make use of the request library in order to make the requests from the ExchangeRateApi.
Home-page: https://github.com/TONYSTARK-EDITH/ExchangeRateApi.git
Author: Tony Stark
Author-email: manthirajak@gmail.com
License: UNKNOWN
Keywords: ExchangeRate,ExchangeRateApi,python,terminal,ExchangeRates
Platform: UNKNOWN
Classifier: Programming Language :: Python :: 3
Classifier: License :: OSI Approved :: MIT License
Classifier: Operating System :: OS Independent
Requires-Python: >=3.0
